evocarshare/__init__.py
evocarshare/api_typing.py
evocarshare/data_types.py
evocarshare/evo_api.py
evocarshare/exceptions.py
evocarshare-0.0.2.dist-info/LICENSE
evocarshare-0.0.2.dist-info/METADATA
evocarshare-0.0.2.dist-info/WHEEL
evocarshare-0.0.2.dist-info/RECORD
