Metadata-Version: 2.3
Name: evocarshare
Version: 0.0.2
Summary: Access data from the Evo Car Share api
Author: Jazzz
Author-email: 473256+jazzz@users.noreply.github.com
Requires-Python: >=3.11,<4.0
Classifier: Programming Language :: Python :: 3
Classifier: Programming Language :: Python :: 3.11
Classifier: Programming Language :: Python :: 3.12
Classifier: Programming Language :: Python :: 3.13
Requires-Dist: aiohttp (>=3.6.0,<4.0.0)
Requires-Dist: haversine (>=2.8.1,<3.0.0)
Project-URL: Documentation, https://github.com/jazzz/evocarshare-py
Project-URL: Repository, https://github.com/jazzz/evocarshare-py
